vivainsights/__init__.py
vivainsights/check_inputs.py
vivainsights/check_query.py
vivainsights/color_codes.py
vivainsights/copilot_usage_glint_sentiment.py
vivainsights/create_IV.py
vivainsights/create_bar.py
vivainsights/create_bar_asis.py
vivainsights/create_boxplot.py
vivainsights/create_bubble.py
vivainsights/create_inc.py
vivainsights/create_line.py
vivainsights/create_lorenz.py
vivainsights/create_odds_ratios.py
vivainsights/create_rank.py
vivainsights/create_sankey.py
vivainsights/create_trend.py
vivainsights/export.py
vivainsights/extract_date_range.py
vivainsights/extract_hr.py
vivainsights/g2g_data.py
vivainsights/hrvar_count.py
vivainsights/identify_churn.py
vivainsights/identify_daterange.py
vivainsights/identify_habit.py
vivainsights/identify_holidayweeks.py
vivainsights/identify_inactiveweeks.py
vivainsights/identify_nkw.py
vivainsights/identify_outlier.py
vivainsights/identify_tenure.py
vivainsights/identify_usage_segments.py
vivainsights/import_query.py
vivainsights/keymetrics_scan.py
vivainsights/mt_data.py
vivainsights/network_g2g.py
vivainsights/network_p2p.py
vivainsights/network_summary.py
vivainsights/p2g_data.py
vivainsights/p2p_data.py
vivainsights/p2p_data_sim.py
vivainsights/pq_data.py
vivainsights/totals_col.py
vivainsights/us_to_space.py
vivainsights/xicor.py
vivainsights/data/g2g_data.csv
vivainsights/data/mt_data.csv
vivainsights/data/p2g_data.csv
vivainsights/data/p2p_data.csv
vivainsights/data/pq_data.csv
vivainsights-0.4.2.dist-info/licenses/LICENSE.md
vivainsights-0.4.2.dist-info/METADATA
vivainsights-0.4.2.dist-info/WHEEL
vivainsights-0.4.2.dist-info/top_level.txt
vivainsights-0.4.2.dist-info/RECORD
