Metadata-Version: 2.4
Name: vivainsights
Version: 0.4.2
Summary: Python library to analyze and visualize data from Microsoft Viva Insights.
Home-page: https://github.com/microsoft/vivainsights
Author: Ellen Trinklein
Author-email: Martin Chan <martinchan@microsoft.com>, Aadarsh Indurkhya <aindurkhya@microsoft.com>, Aaron Harrison <aaron.harrison@microsoft.com>, Arghya Mukherjee <arghya.mukherjee@microsoft.com>, Carlos Morales Torrado <carlos.morales@microsoft.com>, JJ Walia <jjwalia@microsoft.com>, Kari Eifler <karieifler@microsoft.com>, Sachin Gaikwad <SachinSTL23@gmail.com>
License-Expression: MIT
Project-URL: Homepage, https://github.com/microsoft/vivainsights-py
Project-URL: Bug Tracker, https://github.com/microsoft/vivainsights-py/issues
Classifier: Programming Language :: Python :: 3
Classifier: Operating System :: OS Independent
Requires-Python: >=3.7
License-File: LICENSE.md
Requires-Dist: seaborn
Requires-Dist: pandas
Requires-Dist: matplotlib
Requires-Dist: matplotlib-inline
Requires-Dist: scipy
Requires-Dist: numpy
Requires-Dist: igraph
Requires-Dist: plotly
Requires-Dist: scikit-learn
Requires-Dist: setuptools
Requires-Dist: adjustText
Dynamic: home-page
Dynamic: license-file
